alactions/__init__.py
alactions/alcli.py
alactions/allib.py
alactions/pipeline.yaml
alactions/pypi.py
alactions/setup.py
alactions/skeleton.py
alactions/tt.txt
alactions/utils.py
alactions-0.0.11.dist-info/LICENSE.txt
alactions-0.0.11.dist-info/METADATA
alactions-0.0.11.dist-info/WHEEL
alactions-0.0.11.dist-info/top_level.txt
alactions-0.0.11.dist-info/RECORD
