Metadata-Version: 2.1
Name: alactions
Version: 0.0.11
Summary: Add a short description here!
Home-page: https://github.com/pyscaffold/pyscaffold/
Author: Julian Mulla
Author-email: jmulla@gmail.com
License: MIT
Project-URL: Documentation, https://pyscaffold.org/
Platform: any
Classifier: Development Status :: 4 - Beta
Classifier: Programming Language :: Python
License-File: LICENSE.txt
Requires-Dist: click
Requires-Dist: ploomber
Requires-Dist: ruamel.yaml
Requires-Dist: importlib-metadata ; python_version < "3.8"
Provides-Extra: testing
Requires-Dist: setuptools ; extra == 'testing'
Requires-Dist: pytest ; extra == 'testing'
Requires-Dist: pytest-cov ; extra == 'testing'
